odoo/addons/account_asset_management_stock_lot/README.rst
odoo/addons/account_asset_management_stock_lot/__init__.py
odoo/addons/account_asset_management_stock_lot/__manifest__.py
odoo/addons/account_asset_management_stock_lot/i18n/account_asset_management_stock_lot.pot
odoo/addons/account_asset_management_stock_lot/i18n/it.po
odoo/addons/account_asset_management_stock_lot/models/__init__.py
odoo/addons/account_asset_management_stock_lot/models/account_asset.py
odoo/addons/account_asset_management_stock_lot/models/stock_lot.py
odoo/addons/account_asset_management_stock_lot/readme/CONTRIBUTORS.md
odoo/addons/account_asset_management_stock_lot/readme/DESCRIPTION.md
odoo/addons/account_asset_management_stock_lot/static/description/icon.png
odoo/addons/account_asset_management_stock_lot/static/description/index.html
odoo/addons/account_asset_management_stock_lot/views/account_asset.xml
odoo_addon_account_asset_management_stock_lot-17.0.1.0.0.4.dist-info/METADATA
odoo_addon_account_asset_management_stock_lot-17.0.1.0.0.4.dist-info/WHEEL
odoo_addon_account_asset_management_stock_lot-17.0.1.0.0.4.dist-info/top_level.txt
odoo_addon_account_asset_management_stock_lot-17.0.1.0.0.4.dist-info/RECORD
